README.md
setup.cfg
setup.py
beetles/__init__.py
beetles/__main__.py
beetles/dataset.py
beetles/extract_data.py
beetles/heuristics.py
beetles/infer.py
beetles/inference_utils.py
beetles/interactive_plot.py
beetles/simple_labeler.py
beetles/train.py
beetles.egg-info/PKG-INFO
beetles.egg-info/SOURCES.txt
beetles.egg-info/dependency_links.txt
beetles.egg-info/entry_points.txt
beetles.egg-info/requires.txt
beetles.egg-info/top_level.txt
beetles/models/__init__.py
beetles/models/attn.py
beetles/models/base_model.py
beetles/models/simple_cnn.py
beetles/models/unet_1d.py
beetles/resources/annotations_key.json
beetles/resources/hmm_weights.json